ldpy/__init__.py
ldpy/__main__.py
ldpy/ldpy.py
ldpy/grun/lib.py
ldpy/grun/util.py
ldpy/rewriter/IndentedStringWriter.py
ldpy/rewriter/LDPythonRewriter.py
ldpy/rewriter/MultiChannelTokenStream.py
ldpy/rewriter/Result.py
ldpy/rewriter/__init__.py
ldpy/rewriter/antlr/LDPythonLexer.py
ldpy/rewriter/antlr/LDPythonParser.py
ldpy/rewriter/antlr/LDPythonVisitor.py
ldpy/sparql/builtin.py
linked_data_python-0.0.4.dist-info/LICENSE.md
linked_data_python-0.0.4.dist-info/METADATA
linked_data_python-0.0.4.dist-info/WHEEL
linked_data_python-0.0.4.dist-info/entry_points.txt
linked_data_python-0.0.4.dist-info/top_level.txt
linked_data_python-0.0.4.dist-info/RECORD
