Metadata-Version: 2.1
Name: linked-data-python
Version: 0.0.4
Summary: The python package "linked-data-python" can execute .ldpy files and run an interactive ldpy console.
Home-page: https://gitlab.com/coswot/ldpy
Author: Maxime Lefrançois
Author-email: maxime.lefrancois@emse.fr
License: MIT
Platform: any
Classifier: License :: OSI Approved :: MIT License
Classifier: Programming Language :: Python :: 3
Classifier: Programming Language :: Python :: 3.7
Classifier: Programming Language :: Python :: 3.8
Classifier: Programming Language :: Python :: 3.9
Classifier: Programming Language :: Python :: 3.10
Classifier: Topic :: Software Development :: Libraries :: Python Modules
Classifier: Operating System :: OS Independent
Classifier: Natural Language :: English
Requires-Python: >=3.7
Requires-Dist: antlr4-python3-runtime
Requires-Dist: ideas
Requires-Dist: rdflib
